link/__init__.py
link/parallel/__init__.py
link/parallel/core.py
link/parallel/driver.py
link/parallel/mapper.py
link/parallel/reducer.py
link/parallel/drivers/__init__.py
link/parallel/drivers/ipython.py
link/parallel/drivers/process.py
link/parallel/drivers/test/__init__.py
link/parallel/drivers/test/ipython.py
link/parallel/drivers/test/process.py
link/parallel/test/__init__.py
link/parallel/test/core.py
link/parallel/test/driver.py
link/parallel/test/mapper.py
link/parallel/test/reducer.py
link.parallel-1.1.dist-info/DESCRIPTION.rst
link.parallel-1.1.dist-info/METADATA
link.parallel-1.1.dist-info/RECORD
link.parallel-1.1.dist-info/WHEEL
link.parallel-1.1.dist-info/metadata.json
link.parallel-1.1.dist-info/top_level.txt
