Metadata-Version: 2.0
Name: link.parallel
Version: 1.1
Summary: Parallel computing framework
Home-page: https://github.com/linkdd/link.parallel
Author: David Delassus
Author-email: david.jose.delassus@gmail.com
License: MIT
Keywords: link parallel computing map reduce
Platform: UNKNOWN
Classifier: Development Status :: 5 - Production/Stable
Classifier: License :: OSI Approved :: MIT License
Classifier: Operating System :: OS Independent
Classifier: Topic :: Utilities
Classifier: Topic :: Software Development :: Libraries :: Python Modules
Classifier: Intended Audience :: Developers
Classifier: Programming Language :: Python
Classifier: Programming Language :: Python :: 2.7
Classifier: Programming Language :: Python :: 3
Classifier: Programming Language :: Python :: 3.4
Classifier: Programming Language :: Python :: 3.5
Classifier: Programming Language :: Python :: Implementation :: CPython
Requires-Dist: b3j0f.conf (>=0.3.19)
Requires-Dist: dill (>=0.2.5)
Requires-Dist: ipython[parallel] (>=5.0.0)
Requires-Dist: link.kvstore (>=1.0)
Requires-Dist: link.middleware (>=1.5)
Requires-Dist: six (>=1.10.0)
